{
  "type": "File",
  "start": 0,
  "end": 426,
  "loc": {
    "start": {
      "line": 1,
      "column": 0
    },
    "end": {
      "line": 22,
      "column": 0
    }
  },
  "program": {
    "type": "Program",
    "start": 0,
    "end": 426,
    "loc": {
      "start": {
        "line": 1,
        "column": 0
      },
      "end": {
        "line": 22,
        "column": 0
      }
    },
    "sourceType": "module",
    "body": [
      {
        "type": "ExportNamedDeclaration",
        "start": 131,
        "end": 424,
        "loc": {
          "start": {
            "line": 7,
            "column": 0
          },
          "end": {
            "line": 21,
            "column": 1
          }
        },
        "specifiers": [],
        "source": null,
        "declaration": {
          "type": "FunctionDeclaration",
          "start": 138,
          "end": 424,
          "loc": {
            "start": {
              "line": 7,
              "column": 7
            },
            "end": {
              "line": 21,
              "column": 1
            }
          },
          "id": {
            "type": "Identifier",
            "start": 147,
            "end": 158,
            "loc": {
              "start": {
                "line": 7,
                "column": 16
              },
              "end": {
                "line": 7,
                "column": 27
              },
              "identifierName": "singleModel"
            },
            "name": "singleModel",
            "leadingComments": null
          },
          "generator": false,
          "expression": false,
          "async": false,
          "params": [
            {
              "type": "Identifier",
              "start": 160,
              "end": 165,
              "loc": {
                "start": {
                  "line": 7,
                  "column": 29
                },
                "end": {
                  "line": 7,
                  "column": 34
                },
                "identifierName": "clazz"
              },
              "name": "clazz"
            }
          ],
          "body": {
            "type": "BlockStatement",
            "start": 167,
            "end": 424,
            "loc": {
              "start": {
                "line": 7,
                "column": 36
              },
              "end": {
                "line": 21,
                "column": 1
              }
            },
            "body": [
              {
                "type": "VariableDeclaration",
                "start": 172,
                "end": 184,
                "loc": {
                  "start": {
                    "line": 8,
                    "column": 2
                  },
                  "end": {
                    "line": 8,
                    "column": 14
                  }
                },
                "declarations": [
                  {
                    "type": "VariableDeclarator",
                    "start": 176,
                    "end": 184,
                    "loc": {
                      "start": {
                        "line": 8,
                        "column": 6
                      },
                      "end": {
                        "line": 8,
                        "column": 14
                      }
                    },
                    "id": {
                      "type": "Identifier",
                      "start": 176,
                      "end": 184,
                      "loc": {
                        "start": {
                          "line": 8,
                          "column": 6
                        },
                        "end": {
                          "line": 8,
                          "column": 14
                        },
                        "identifierName": "instance"
                      },
                      "name": "instance"
                    },
                    "init": null
                  }
                ],
                "kind": "let"
              },
              {
                "type": "ReturnStatement",
                "start": 188,
                "end": 421,
                "loc": {
                  "start": {
                    "line": 9,
                    "column": 2
                  },
                  "end": {
                    "line": 20,
                    "column": 3
                  }
                },
                "argument": {
                  "type": "ClassExpression",
                  "start": 195,
                  "end": 421,
                  "loc": {
                    "start": {
                      "line": 9,
                      "column": 9
                    },
                    "end": {
                      "line": 20,
                      "column": 3
                    }
                  },
                  "id": {
                    "type": "Identifier",
                    "start": 201,
                    "end": 212,
                    "loc": {
                      "start": {
                        "line": 9,
                        "column": 15
                      },
                      "end": {
                        "line": 9,
                        "column": 26
                      },
                      "identifierName": "SingleClass"
                    },
                    "name": "SingleClass"
                  },
                  "superClass": {
                    "type": "Identifier",
                    "start": 221,
                    "end": 226,
                    "loc": {
                      "start": {
                        "line": 9,
                        "column": 35
                      },
                      "end": {
                        "line": 9,
                        "column": 40
                      },
                      "identifierName": "clazz"
                    },
                    "name": "clazz"
                  },
                  "body": {
                    "type": "ClassBody",
                    "start": 227,
                    "end": 421,
                    "loc": {
                      "start": {
                        "line": 9,
                        "column": 41
                      },
                      "end": {
                        "line": 20,
                        "column": 3
                      }
                    },
                    "body": [
                      {
                        "type": "ClassMethod",
                        "start": 284,
                        "end": 416,
                        "loc": {
                          "start": {
                            "line": 13,
                            "column": 4
                          },
                          "end": {
                            "line": 19,
                            "column": 5
                          }
                        },
                        "static": false,
                        "computed": false,
                        "key": {
                          "type": "Identifier",
                          "start": 284,
                          "end": 295,
                          "loc": {
                            "start": {
                              "line": 13,
                              "column": 4
                            },
                            "end": {
                              "line": 13,
                              "column": 15
                            },
                            "identifierName": "constructor"
                          },
                          "name": "constructor",
                          "leadingComments": null
                        },
                        "kind": "constructor",
                        "id": null,
                        "generator": false,
                        "expression": false,
                        "async": false,
                        "params": [
                          {
                            "type": "RestElement",
                            "start": 297,
                            "end": 304,
                            "loc": {
                              "start": {
                                "line": 13,
                                "column": 17
                              },
                              "end": {
                                "line": 13,
                                "column": 24
                              }
                            },
                            "argument": {
                              "type": "Identifier",
                              "start": 300,
                              "end": 304,
                              "loc": {
                                "start": {
                                  "line": 13,
                                  "column": 20
                                },
                                "end": {
                                  "line": 13,
                                  "column": 24
                                },
                                "identifierName": "args"
                              },
                              "name": "args"
                            }
                          }
                        ],
                        "body": {
                          "type": "BlockStatement",
                          "start": 306,
                          "end": 416,
                          "loc": {
                            "start": {
                              "line": 13,
                              "column": 26
                            },
                            "end": {
                              "line": 19,
                              "column": 5
                            }
                          },
                          "body": [
                            {
                              "type": "IfStatement",
                              "start": 315,
                              "end": 364,
                              "loc": {
                                "start": {
                                  "line": 14,
                                  "column": 6
                                },
                                "end": {
                                  "line": 16,
                                  "column": 7
                                }
                              },
                              "test": {
                                "type": "Identifier",
                                "start": 319,
                                "end": 327,
                                "loc": {
                                  "start": {
                                    "line": 14,
                                    "column": 10
                                  },
                                  "end": {
                                    "line": 14,
                                    "column": 18
                                  },
                                  "identifierName": "instance"
                                },
                                "name": "instance"
                              },
                              "consequent": {
                                "type": "BlockStatement",
                                "start": 329,
                                "end": 364,
                                "loc": {
                                  "start": {
                                    "line": 14,
                                    "column": 20
                                  },
                                  "end": {
                                    "line": 16,
                                    "column": 7
                                  }
                                },
                                "body": [
                                  {
                                    "type": "ReturnStatement",
                                    "start": 340,
                                    "end": 355,
                                    "loc": {
                                      "start": {
                                        "line": 15,
                                        "column": 8
                                      },
                                      "end": {
                                        "line": 15,
                                        "column": 23
                                      }
                                    },
                                    "argument": {
                                      "type": "Identifier",
                                      "start": 347,
                                      "end": 355,
                                      "loc": {
                                        "start": {
                                          "line": 15,
                                          "column": 15
                                        },
                                        "end": {
                                          "line": 15,
                                          "column": 23
                                        },
                                        "identifierName": "instance"
                                      },
                                      "name": "instance"
                                    }
                                  }
                                ],
                                "directives": []
                              },
                              "alternate": null
                            },
                            {
                              "type": "ExpressionStatement",
                              "start": 372,
                              "end": 386,
                              "loc": {
                                "start": {
                                  "line": 17,
                                  "column": 6
                                },
                                "end": {
                                  "line": 17,
                                  "column": 20
                                }
                              },
                              "expression": {
                                "type": "CallExpression",
                                "start": 372,
                                "end": 386,
                                "loc": {
                                  "start": {
                                    "line": 17,
                                    "column": 6
                                  },
                                  "end": {
                                    "line": 17,
                                    "column": 20
                                  }
                                },
                                "callee": {
                                  "type": "Super",
                                  "start": 372,
                                  "end": 377,
                                  "loc": {
                                    "start": {
                                      "line": 17,
                                      "column": 6
                                    },
                                    "end": {
                                      "line": 17,
                                      "column": 11
                                    }
                                  }
                                },
                                "arguments": [
                                  {
                                    "type": "SpreadElement",
                                    "start": 378,
                                    "end": 385,
                                    "loc": {
                                      "start": {
                                        "line": 17,
                                        "column": 12
                                      },
                                      "end": {
                                        "line": 17,
                                        "column": 19
                                      }
                                    },
                                    "argument": {
                                      "type": "Identifier",
                                      "start": 381,
                                      "end": 385,
                                      "loc": {
                                        "start": {
                                          "line": 17,
                                          "column": 15
                                        },
                                        "end": {
                                          "line": 17,
                                          "column": 19
                                        },
                                        "identifierName": "args"
                                      },
                                      "name": "args"
                                    }
                                  }
                                ]
                              }
                            },
                            {
                              "type": "ExpressionStatement",
                              "start": 394,
                              "end": 409,
                              "loc": {
                                "start": {
                                  "line": 18,
                                  "column": 6
                                },
                                "end": {
                                  "line": 18,
                                  "column": 21
                                }
                              },
                              "expression": {
                                "type": "AssignmentExpression",
                                "start": 394,
                                "end": 409,
                                "loc": {
                                  "start": {
                                    "line": 18,
                                    "column": 6
                                  },
                                  "end": {
                                    "line": 18,
                                    "column": 21
                                  }
                                },
                                "operator": "=",
                                "left": {
                                  "type": "Identifier",
                                  "start": 394,
                                  "end": 402,
                                  "loc": {
                                    "start": {
                                      "line": 18,
                                      "column": 6
                                    },
                                    "end": {
                                      "line": 18,
                                      "column": 14
                                    },
                                    "identifierName": "instance"
                                  },
                                  "name": "instance"
                                },
                                "right": {
                                  "type": "ThisExpression",
                                  "start": 405,
                                  "end": 409,
                                  "loc": {
                                    "start": {
                                      "line": 18,
                                      "column": 17
                                    },
                                    "end": {
                                      "line": 18,
                                      "column": 21
                                    }
                                  }
                                }
                              }
                            }
                          ],
                          "directives": []
                        },
                        "leadingComments": [
                          {
                            "type": "CommentBlock",
                            "value": "*\r\n     * @param {...Object} args\r\n     ",
                            "start": 234,
                            "end": 278,
                            "loc": {
                              "start": {
                                "line": 10,
                                "column": 4
                              },
                              "end": {
                                "line": 12,
                                "column": 7
                              }
                            }
                          }
                        ]
                      }
                    ]
                  }
                }
              }
            ],
            "directives": []
          },
          "leadingComments": [
            {
              "type": "CommentLine",
              "value": " @ts-check",
              "start": 0,
              "end": 12,
              "loc": {
                "start": {
                  "line": 1,
                  "column": 0
                },
                "end": {
                  "line": 1,
                  "column": 12
                }
              }
            },
            {
              "type": "CommentBlock",
              "value": "*\r\n * 通用的单例模式\r\n * @param {Object} clazz 需要包装为单例的类型\r\n * @returns {Object} 包装后的单例模式类，使用 {@code new} 创建将只在第一次有效\r\n ",
              "start": 14,
              "end": 129,
              "loc": {
                "start": {
                  "line": 2,
                  "column": 0
                },
                "end": {
                  "line": 6,
                  "column": 3
                }
              }
            }
          ],
          "trailingComments": []
        },
        "leadingComments": [
          {
            "type": "CommentLine",
            "value": " @ts-check",
            "start": 0,
            "end": 12,
            "loc": {
              "start": {
                "line": 1,
                "column": 0
              },
              "end": {
                "line": 1,
                "column": 12
              }
            }
          },
          {
            "type": "CommentBlock",
            "value": "*\r\n * 通用的单例模式\r\n * @param {Object} clazz 需要包装为单例的类型\r\n * @returns {Object} 包装后的单例模式类，使用 {@code new} 创建将只在第一次有效\r\n ",
            "start": 14,
            "end": 129,
            "loc": {
              "start": {
                "line": 2,
                "column": 0
              },
              "end": {
                "line": 6,
                "column": 3
              }
            }
          }
        ]
      }
    ],
    "directives": []
  },
  "comments": [
    {
      "type": "CommentLine",
      "value": " @ts-check",
      "start": 0,
      "end": 12,
      "loc": {
        "start": {
          "line": 1,
          "column": 0
        },
        "end": {
          "line": 1,
          "column": 12
        }
      }
    },
    {
      "type": "CommentBlock",
      "value": "*\r\n * 通用的单例模式\r\n * @param {Object} clazz 需要包装为单例的类型\r\n * @returns {Object} 包装后的单例模式类，使用 {@code new} 创建将只在第一次有效\r\n ",
      "start": 14,
      "end": 129,
      "loc": {
        "start": {
          "line": 2,
          "column": 0
        },
        "end": {
          "line": 6,
          "column": 3
        }
      }
    },
    {
      "type": "CommentBlock",
      "value": "*\r\n     * @param {...Object} args\r\n     ",
      "start": 234,
      "end": 278,
      "loc": {
        "start": {
          "line": 10,
          "column": 4
        },
        "end": {
          "line": 12,
          "column": 7
        }
      }
    }
  ],
  "tokens": [
    {
      "type": "CommentLine",
      "value": " @ts-check",
      "start": 0,
      "end": 12,
      "loc": {
        "start": {
          "line": 1,
          "column": 0
        },
        "end": {
          "line": 1,
          "column": 12
        }
      }
    },
    {
      "type": "CommentBlock",
      "value": "*\r\n * 通用的单例模式\r\n * @param {Object} clazz 需要包装为单例的类型\r\n * @returns {Object} 包装后的单例模式类，使用 {@code new} 创建将只在第一次有效\r\n ",
      "start": 14,
      "end": 129,
      "loc": {
        "start": {
          "line": 2,
          "column": 0
        },
        "end": {
          "line": 6,
          "column": 3
        }
      }
    },
    {
      "type": {
        "label": "export",
        "keyword": "export",
        "beforeExpr": false,
        "startsExpr": false,
        "rightAssociative": false,
        "isLoop": false,
        "isAssign": false,
        "prefix": false,
        "postfix": false,
        "binop": null,
        "updateContext": null
      },
      "value": "export",
      "start": 131,
      "end": 137,
      "loc": {
        "start": {
          "line": 7,
          "column": 0
        },
        "end": {
          "line": 7,
          "column": 6
        }
      }
    },
    {
      "type": {
        "label": "function",
        "keyword": "function",
        "beforeExpr": false,
        "startsExpr": true,
        "rightAssociative": false,
        "isLoop": false,
        "isAssign": false,
        "prefix": false,
        "postfix": false,
        "binop": null
      },
      "value": "function",
      "start": 138,
      "end": 146,
      "loc": {
        "start": {
          "line": 7,
          "column": 7
        },
        "end": {
          "line": 7,
          "column": 15
        }
      }
    },
    {
      "type": {
        "label": "name",
        "beforeExpr": false,
        "startsExpr": true,
        "rightAssociative": false,
        "isLoop": false,
        "isAssign": false,
        "prefix": false,
        "postfix": false,
        "binop": null
      },
      "value": "singleModel",
      "start": 147,
      "end": 158,
      "loc": {
        "start": {
          "line": 7,
          "column": 16
        },
        "end": {
          "line": 7,
          "column": 27
        }
      }
    },
    {
      "type": {
        "label": "(",
        "beforeExpr": true,
        "startsExpr": true,
        "rightAssociative": false,
        "isLoop": false,
        "isAssign": false,
        "prefix": false,
        "postfix": false,
        "binop": null
      },
      "start": 159,
      "end": 160,
      "loc": {
        "start": {
          "line": 7,
          "column": 28
        },
        "end": {
          "line": 7,
          "column": 29
        }
      }
    },
    {
      "type": {
        "label": "name",
        "beforeExpr": false,
        "startsExpr": true,
        "rightAssociative": false,
        "isLoop": false,
        "isAssign": false,
        "prefix": false,
        "postfix": false,
        "binop": null
      },
      "value": "clazz",
      "start": 160,
      "end": 165,
      "loc": {
        "start": {
          "line": 7,
          "column": 29
        },
        "end": {
          "line": 7,
          "column": 34
        }
      }
    },
    {
      "type": {
        "label": ")",
        "beforeExpr": false,
        "startsExpr": false,
        "rightAssociative": false,
        "isLoop": false,
        "isAssign": false,
        "prefix": false,
        "postfix": false,
        "binop": null
      },
      "start": 165,
      "end": 166,
      "loc": {
        "start": {
          "line": 7,
          "column": 34
        },
        "end": {
          "line": 7,
          "column": 35
        }
      }
    },
    {
      "type": {
        "label": "{",
        "beforeExpr": true,
        "startsExpr": true,
        "rightAssociative": false,
        "isLoop": false,
        "isAssign": false,
        "prefix": false,
        "postfix": false,
        "binop": null
      },
      "start": 167,
      "end": 168,
      "loc": {
        "start": {
          "line": 7,
          "column": 36
        },
        "end": {
          "line": 7,
          "column": 37
        }
      }
    },
    {
      "type": {
        "label": "let",
        "keyword": "let",
        "beforeExpr": false,
        "startsExpr": false,
        "rightAssociative": false,
        "isLoop": false,
        "isAssign": false,
        "prefix": false,
        "postfix": false,
        "binop": null,
        "updateContext": null
      },
      "value": "let",
      "start": 172,
      "end": 175,
      "loc": {
        "start": {
          "line": 8,
          "column": 2
        },
        "end": {
          "line": 8,
          "column": 5
        }
      }
    },
    {
      "type": {
        "label": "name",
        "beforeExpr": false,
        "startsExpr": true,
        "rightAssociative": false,
        "isLoop": false,
        "isAssign": false,
        "prefix": false,
        "postfix": false,
        "binop": null
      },
      "value": "instance",
      "start": 176,
      "end": 184,
      "loc": {
        "start": {
          "line": 8,
          "column": 6
        },
        "end": {
          "line": 8,
          "column": 14
        }
      }
    },
    {
      "type": {
        "label": "return",
        "keyword": "return",
        "beforeExpr": true,
        "startsExpr": false,
        "rightAssociative": false,
        "isLoop": false,
        "isAssign": false,
        "prefix": false,
        "postfix": false,
        "binop": null,
        "updateContext": null
      },
      "value": "return",
      "start": 188,
      "end": 194,
      "loc": {
        "start": {
          "line": 9,
          "column": 2
        },
        "end": {
          "line": 9,
          "column": 8
        }
      }
    },
    {
      "type": {
        "label": "class",
        "keyword": "class",
        "beforeExpr": false,
        "startsExpr": false,
        "rightAssociative": false,
        "isLoop": false,
        "isAssign": false,
        "prefix": false,
        "postfix": false,
        "binop": null,
        "updateContext": null
      },
      "value": "class",
      "start": 195,
      "end": 200,
      "loc": {
        "start": {
          "line": 9,
          "column": 9
        },
        "end": {
          "line": 9,
          "column": 14
        }
      }
    },
    {
      "type": {
        "label": "name",
        "beforeExpr": false,
        "startsExpr": true,
        "rightAssociative": false,
        "isLoop": false,
        "isAssign": false,
        "prefix": false,
        "postfix": false,
        "binop": null
      },
      "value": "SingleClass",
      "start": 201,
      "end": 212,
      "loc": {
        "start": {
          "line": 9,
          "column": 15
        },
        "end": {
          "line": 9,
          "column": 26
        }
      }
    },
    {
      "type": {
        "label": "extends",
        "keyword": "extends",
        "beforeExpr": true,
        "startsExpr": false,
        "rightAssociative": false,
        "isLoop": false,
        "isAssign": false,
        "prefix": false,
        "postfix": false,
        "binop": null,
        "updateContext": null
      },
      "value": "extends",
      "start": 213,
      "end": 220,
      "loc": {
        "start": {
          "line": 9,
          "column": 27
        },
        "end": {
          "line": 9,
          "column": 34
        }
      }
    },
    {
      "type": {
        "label": "name",
        "beforeExpr": false,
        "startsExpr": true,
        "rightAssociative": false,
        "isLoop": false,
        "isAssign": false,
        "prefix": false,
        "postfix": false,
        "binop": null
      },
      "value": "clazz",
      "start": 221,
      "end": 226,
      "loc": {
        "start": {
          "line": 9,
          "column": 35
        },
        "end": {
          "line": 9,
          "column": 40
        }
      }
    },
    {
      "type": {
        "label": "{",
        "beforeExpr": true,
        "startsExpr": true,
        "rightAssociative": false,
        "isLoop": false,
        "isAssign": false,
        "prefix": false,
        "postfix": false,
        "binop": null
      },
      "start": 227,
      "end": 228,
      "loc": {
        "start": {
          "line": 9,
          "column": 41
        },
        "end": {
          "line": 9,
          "column": 42
        }
      }
    },
    {
      "type": "CommentBlock",
      "value": "*\r\n     * @param {...Object} args\r\n     ",
      "start": 234,
      "end": 278,
      "loc": {
        "start": {
          "line": 10,
          "column": 4
        },
        "end": {
          "line": 12,
          "column": 7
        }
      }
    },
    {
      "type": {
        "label": "name",
        "beforeExpr": false,
        "startsExpr": true,
        "rightAssociative": false,
        "isLoop": false,
        "isAssign": false,
        "prefix": false,
        "postfix": false,
        "binop": null
      },
      "value": "constructor",
      "start": 284,
      "end": 295,
      "loc": {
        "start": {
          "line": 13,
          "column": 4
        },
        "end": {
          "line": 13,
          "column": 15
        }
      }
    },
    {
      "type": {
        "label": "(",
        "beforeExpr": true,
        "startsExpr": true,
        "rightAssociative": false,
        "isLoop": false,
        "isAssign": false,
        "prefix": false,
        "postfix": false,
        "binop": null
      },
      "start": 296,
      "end": 297,
      "loc": {
        "start": {
          "line": 13,
          "column": 16
        },
        "end": {
          "line": 13,
          "column": 17
        }
      }
    },
    {
      "type": {
        "label": "...",
        "beforeExpr": true,
        "startsExpr": false,
        "rightAssociative": false,
        "isLoop": false,
        "isAssign": false,
        "prefix": false,
        "postfix": false,
        "binop": null,
        "updateContext": null
      },
      "start": 297,
      "end": 300,
      "loc": {
        "start": {
          "line": 13,
          "column": 17
        },
        "end": {
          "line": 13,
          "column": 20
        }
      }
    },
    {
      "type": {
        "label": "name",
        "beforeExpr": false,
        "startsExpr": true,
        "rightAssociative": false,
        "isLoop": false,
        "isAssign": false,
        "prefix": false,
        "postfix": false,
        "binop": null
      },
      "value": "args",
      "start": 300,
      "end": 304,
      "loc": {
        "start": {
          "line": 13,
          "column": 20
        },
        "end": {
          "line": 13,
          "column": 24
        }
      }
    },
    {
      "type": {
        "label": ")",
        "beforeExpr": false,
        "startsExpr": false,
        "rightAssociative": false,
        "isLoop": false,
        "isAssign": false,
        "prefix": false,
        "postfix": false,
        "binop": null
      },
      "start": 304,
      "end": 305,
      "loc": {
        "start": {
          "line": 13,
          "column": 24
        },
        "end": {
          "line": 13,
          "column": 25
        }
      }
    },
    {
      "type": {
        "label": "{",
        "beforeExpr": true,
        "startsExpr": true,
        "rightAssociative": false,
        "isLoop": false,
        "isAssign": false,
        "prefix": false,
        "postfix": false,
        "binop": null
      },
      "start": 306,
      "end": 307,
      "loc": {
        "start": {
          "line": 13,
          "column": 26
        },
        "end": {
          "line": 13,
          "column": 27
        }
      }
    },
    {
      "type": {
        "label": "if",
        "keyword": "if",
        "beforeExpr": false,
        "startsExpr": false,
        "rightAssociative": false,
        "isLoop": false,
        "isAssign": false,
        "prefix": false,
        "postfix": false,
        "binop": null,
        "updateContext": null
      },
      "value": "if",
      "start": 315,
      "end": 317,
      "loc": {
        "start": {
          "line": 14,
          "column": 6
        },
        "end": {
          "line": 14,
          "column": 8
        }
      }
    },
    {
      "type": {
        "label": "(",
        "beforeExpr": true,
        "startsExpr": true,
        "rightAssociative": false,
        "isLoop": false,
        "isAssign": false,
        "prefix": false,
        "postfix": false,
        "binop": null
      },
      "start": 318,
      "end": 319,
      "loc": {
        "start": {
          "line": 14,
          "column": 9
        },
        "end": {
          "line": 14,
          "column": 10
        }
      }
    },
    {
      "type": {
        "label": "name",
        "beforeExpr": false,
        "startsExpr": true,
        "rightAssociative": false,
        "isLoop": false,
        "isAssign": false,
        "prefix": false,
        "postfix": false,
        "binop": null
      },
      "value": "instance",
      "start": 319,
      "end": 327,
      "loc": {
        "start": {
          "line": 14,
          "column": 10
        },
        "end": {
          "line": 14,
          "column": 18
        }
      }
    },
    {
      "type": {
        "label": ")",
        "beforeExpr": false,
        "startsExpr": false,
        "rightAssociative": false,
        "isLoop": false,
        "isAssign": false,
        "prefix": false,
        "postfix": false,
        "binop": null
      },
      "start": 327,
      "end": 328,
      "loc": {
        "start": {
          "line": 14,
          "column": 18
        },
        "end": {
          "line": 14,
          "column": 19
        }
      }
    },
    {
      "type": {
        "label": "{",
        "beforeExpr": true,
        "startsExpr": true,
        "rightAssociative": false,
        "isLoop": false,
        "isAssign": false,
        "prefix": false,
        "postfix": false,
        "binop": null
      },
      "start": 329,
      "end": 330,
      "loc": {
        "start": {
          "line": 14,
          "column": 20
        },
        "end": {
          "line": 14,
          "column": 21
        }
      }
    },
    {
      "type": {
        "label": "return",
        "keyword": "return",
        "beforeExpr": true,
        "startsExpr": false,
        "rightAssociative": false,
        "isLoop": false,
        "isAssign": false,
        "prefix": false,
        "postfix": false,
        "binop": null,
        "updateContext": null
      },
      "value": "return",
      "start": 340,
      "end": 346,
      "loc": {
        "start": {
          "line": 15,
          "column": 8
        },
        "end": {
          "line": 15,
          "column": 14
        }
      }
    },
    {
      "type": {
        "label": "name",
        "beforeExpr": false,
        "startsExpr": true,
        "rightAssociative": false,
        "isLoop": false,
        "isAssign": false,
        "prefix": false,
        "postfix": false,
        "binop": null
      },
      "value": "instance",
      "start": 347,
      "end": 355,
      "loc": {
        "start": {
          "line": 15,
          "column": 15
        },
        "end": {
          "line": 15,
          "column": 23
        }
      }
    },
    {
      "type": {
        "label": "}",
        "beforeExpr": false,
        "startsExpr": false,
        "rightAssociative": false,
        "isLoop": false,
        "isAssign": false,
        "prefix": false,
        "postfix": false,
        "binop": null
      },
      "start": 363,
      "end": 364,
      "loc": {
        "start": {
          "line": 16,
          "column": 6
        },
        "end": {
          "line": 16,
          "column": 7
        }
      }
    },
    {
      "type": {
        "label": "super",
        "keyword": "super",
        "beforeExpr": false,
        "startsExpr": true,
        "rightAssociative": false,
        "isLoop": false,
        "isAssign": false,
        "prefix": false,
        "postfix": false,
        "binop": null,
        "updateContext": null
      },
      "value": "super",
      "start": 372,
      "end": 377,
      "loc": {
        "start": {
          "line": 17,
          "column": 6
        },
        "end": {
          "line": 17,
          "column": 11
        }
      }
    },
    {
      "type": {
        "label": "(",
        "beforeExpr": true,
        "startsExpr": true,
        "rightAssociative": false,
        "isLoop": false,
        "isAssign": false,
        "prefix": false,
        "postfix": false,
        "binop": null
      },
      "start": 377,
      "end": 378,
      "loc": {
        "start": {
          "line": 17,
          "column": 11
        },
        "end": {
          "line": 17,
          "column": 12
        }
      }
    },
    {
      "type": {
        "label": "...",
        "beforeExpr": true,
        "startsExpr": false,
        "rightAssociative": false,
        "isLoop": false,
        "isAssign": false,
        "prefix": false,
        "postfix": false,
        "binop": null,
        "updateContext": null
      },
      "start": 378,
      "end": 381,
      "loc": {
        "start": {
          "line": 17,
          "column": 12
        },
        "end": {
          "line": 17,
          "column": 15
        }
      }
    },
    {
      "type": {
        "label": "name",
        "beforeExpr": false,
        "startsExpr": true,
        "rightAssociative": false,
        "isLoop": false,
        "isAssign": false,
        "prefix": false,
        "postfix": false,
        "binop": null
      },
      "value": "args",
      "start": 381,
      "end": 385,
      "loc": {
        "start": {
          "line": 17,
          "column": 15
        },
        "end": {
          "line": 17,
          "column": 19
        }
      }
    },
    {
      "type": {
        "label": ")",
        "beforeExpr": false,
        "startsExpr": false,
        "rightAssociative": false,
        "isLoop": false,
        "isAssign": false,
        "prefix": false,
        "postfix": false,
        "binop": null
      },
      "start": 385,
      "end": 386,
      "loc": {
        "start": {
          "line": 17,
          "column": 19
        },
        "end": {
          "line": 17,
          "column": 20
        }
      }
    },
    {
      "type": {
        "label": "name",
        "beforeExpr": false,
        "startsExpr": true,
        "rightAssociative": false,
        "isLoop": false,
        "isAssign": false,
        "prefix": false,
        "postfix": false,
        "binop": null
      },
      "value": "instance",
      "start": 394,
      "end": 402,
      "loc": {
        "start": {
          "line": 18,
          "column": 6
        },
        "end": {
          "line": 18,
          "column": 14
        }
      }
    },
    {
      "type": {
        "label": "=",
        "beforeExpr": true,
        "startsExpr": false,
        "rightAssociative": false,
        "isLoop": false,
        "isAssign": true,
        "prefix": false,
        "postfix": false,
        "binop": null,
        "updateContext": null
      },
      "value": "=",
      "start": 403,
      "end": 404,
      "loc": {
        "start": {
          "line": 18,
          "column": 15
        },
        "end": {
          "line": 18,
          "column": 16
        }
      }
    },
    {
      "type": {
        "label": "this",
        "keyword": "this",
        "beforeExpr": false,
        "startsExpr": true,
        "rightAssociative": false,
        "isLoop": false,
        "isAssign": false,
        "prefix": false,
        "postfix": false,
        "binop": null,
        "updateContext": null
      },
      "value": "this",
      "start": 405,
      "end": 409,
      "loc": {
        "start": {
          "line": 18,
          "column": 17
        },
        "end": {
          "line": 18,
          "column": 21
        }
      }
    },
    {
      "type": {
        "label": "}",
        "beforeExpr": false,
        "startsExpr": false,
        "rightAssociative": false,
        "isLoop": false,
        "isAssign": false,
        "prefix": false,
        "postfix": false,
        "binop": null
      },
      "start": 415,
      "end": 416,
      "loc": {
        "start": {
          "line": 19,
          "column": 4
        },
        "end": {
          "line": 19,
          "column": 5
        }
      }
    },
    {
      "type": {
        "label": "}",
        "beforeExpr": false,
        "startsExpr": false,
        "rightAssociative": false,
        "isLoop": false,
        "isAssign": false,
        "prefix": false,
        "postfix": false,
        "binop": null
      },
      "start": 420,
      "end": 421,
      "loc": {
        "start": {
          "line": 20,
          "column": 2
        },
        "end": {
          "line": 20,
          "column": 3
        }
      }
    },
    {
      "type": {
        "label": "}",
        "beforeExpr": false,
        "startsExpr": false,
        "rightAssociative": false,
        "isLoop": false,
        "isAssign": false,
        "prefix": false,
        "postfix": false,
        "binop": null
      },
      "start": 423,
      "end": 424,
      "loc": {
        "start": {
          "line": 21,
          "column": 0
        },
        "end": {
          "line": 21,
          "column": 1
        }
      }
    },
    {
      "type": {
        "label": "eof",
        "beforeExpr": false,
        "startsExpr": false,
        "rightAssociative": false,
        "isLoop": false,
        "isAssign": false,
        "prefix": false,
        "postfix": false,
        "binop": null,
        "updateContext": null
      },
      "start": 426,
      "end": 426,
      "loc": {
        "start": {
          "line": 22,
          "column": 0
        },
        "end": {
          "line": 22,
          "column": 0
        }
      }
    }
  ]
}